flask_sqlalchemy_extension/__init__.py
flask_sqlalchemy_extension/func.py
flask_sqlalchemy_extension/mixins.py
flask_sqlalchemy_extension-0.0.5.dist-info/LICENSE
flask_sqlalchemy_extension-0.0.5.dist-info/METADATA
flask_sqlalchemy_extension-0.0.5.dist-info/WHEEL
flask_sqlalchemy_extension-0.0.5.dist-info/top_level.txt
flask_sqlalchemy_extension-0.0.5.dist-info/RECORD
