Metadata-Version: 2.1
Name: flask-sqlalchemy-extension
Version: 0.0.5
Summary: Package provided mixins and extension for sqlalchemy and flask-sqlalchemy packages.
Home-page: https://github.com/dkotlyar/flask-sqlalchemy-extension
Author: Dmitry Kotlyar
Author-email: dm.kotlyar@yandex.ru
License: UNKNOWN
Platform: UNKNOWN
Classifier: Programming Language :: Python :: 3.8
Classifier: License :: OSI Approved :: MIT License
Classifier: Operating System :: OS Independent
Requires-Python: >=3.6
License-File: LICENSE
Requires-Dist: Flask-SQLAlchemy (>=2.5.1)
Requires-Dist: SQLAlchemy (>=1.4.35)
